{"cameraMode":{"drawMode":0,"name":"Shaded","section":"Shading Mode"},"sceneLighting":true,"audioPlay":false,"sceneViewState":{"showFog":true,"showMaterialUpdate":false,"showSkybox":true,"showFlares":true,"showImageEffects":true,"showParticleSystems":true,"showVisualEffectGraphs":true,"m_FxEnabled":true},"in2DMode":false,"pivot":{"x":-0.6949330568313599,"y":2.466384172439575,"z":-9.59797191619873},"rotation":{"x":-0.028111036866903306,"y":0.8620447516441345,"z":-0.04818020015954971,"w":-0.5037978291511536},"size":2.7920432090759279,"orthographic":false}